README.md
setup.cfg
setup.py
anwa/__init__.py
anwa/__main__.py
anwa/activity_detector.py
anwa/algorithm.py
anwa/anwa.ico
anwa/anwa.png
anwa/app_tools.py
anwa/main_click.py
anwa/qtexceptionhook.py
anwa.egg-info/PKG-INFO
anwa.egg-info/SOURCES.txt
anwa.egg-info/dependency_links.txt
anwa.egg-info/top_level.txt