Metadata-Version: 2.1
Name: anwa
Version: 0.2.4
Summary: Automatic animal detection in video
Home-page: https://github.com/mjirik/anwa
Author: Miroslav Jirik
Author-email: miroslav.jirik@gmail.com
License: MIT
Platform: UNKNOWN
Classifier: Development Status :: 3 - Alpha
Classifier: Intended Audience :: Developers
Classifier: Topic :: Scientific/Engineering :: Bio-Informatics
Classifier: License :: OSI Approved :: BSD License
Classifier: Programming Language :: Python :: 3.7
Classifier: Programming Language :: Python :: 3.6
